flare/__init__.py
flare/__main__.py
flare/converters.py
flare/dataclass.py
flare/exceptions.py
flare/py.typed
flare/row.py
flare/utils.py
flare/components/__init__.py
flare/components/base.py
flare/components/button.py
flare/components/functional.py
flare/components/modal.py
flare/components/select.py
flare/context/__init__.py
flare/context/base.py
flare/context/message.py
flare/context/modal.py
flare/internal/README.md
flare/internal/__init__.py
flare/internal/bootstrap.py
flare/internal/event_handler.py
flare/internal/serde.py
hikari_flare-0.1.3.dist-info/LICENSE
hikari_flare-0.1.3.dist-info/METADATA
hikari_flare-0.1.3.dist-info/WHEEL
hikari_flare-0.1.3.dist-info/top_level.txt
hikari_flare-0.1.3.dist-info/RECORD
