Metadata-Version: 2.1
Name: hikari-flare
Version: 0.1.3
Summary: Stateless component manager for hikari with type-safe API.
Maintainer-email: Lunarmagpie <Bambolambo0@gmail.com>, HyperGH <46067571+HyperGH@users.noreply.github.com>
License: MIT
Project-URL: Repository, https://github.com/brazier-dev/hikari-flare/
Classifier: Development Status :: 4 - Beta
Classifier: Framework :: AsyncIO
Classifier: Intended Audience :: Developers
Classifier: Natural Language :: English
Classifier: Topic :: Software Development :: Libraries :: Python Modules
Classifier: Programming Language :: Python :: 3.11
Classifier: Programming Language :: Python :: 3.10
Classifier: Programming Language :: Python :: Implementation :: CPython
Classifier: Programming Language :: Python :: 3 :: Only
Classifier: Topic :: Software Development :: Libraries
Classifier: Topic :: Software Development :: Libraries :: Application Frameworks
Classifier: Topic :: Software Development :: Libraries :: Python Modules
Requires-Python: <3.12,>=3.10
License-File: LICENSE
Requires-Dist: hikari >=2.0.0.dev118
Requires-Dist: sigparse >=3.0.0
Requires-Dist: typing-extensions >=4.4.0
Requires-Dist: colorama ; platform_system == "Windows"
